MANIFEST.in
README.txt
setup.py
django_dynamic_rules.egg-info/PKG-INFO
django_dynamic_rules.egg-info/SOURCES.txt
django_dynamic_rules.egg-info/dependency_links.txt
django_dynamic_rules.egg-info/not-zip-safe
django_dynamic_rules.egg-info/requires.txt
django_dynamic_rules.egg-info/top_level.txt
dynamic_rules/__init__.py
dynamic_rules/admin.py
dynamic_rules/admin_forms.py
dynamic_rules/dynamic_actions.py
dynamic_rules/ext.py
dynamic_rules/models.py
dynamic_rules/sites.py
dynamic_rules/migrations/0001_initial.py
dynamic_rules/migrations/0002_auto__add_field_rule_secondary_object_id.py
dynamic_rules/migrations/__init__.py
dynamic_rules/tests/__init__.py
dynamic_rules/tests/test_admin_forms.py
dynamic_rules/tests/test_dynamic_actions.py
dynamic_rules/tests/test_ext.py
dynamic_rules/tests/test_models.py
dynamic_rules/tests/test_registry.py
example/sample/__init__.py
example/sample/admin.py
example/sample/dynamic_actions.py
example/sample/models.py
requirements/ci.txt
requirements/dev.txt
requirements/dist.txt