Metadata-Version: 1.1
Name: django-dynamic-rules
Version: 0.6.0
Summary: Allows you to create dynamic rules related to a particular model
Home-page: https://github.com/imtapps/django-dynamic-rules
Author: IMT Computer Services
Author-email: webadmin@imtapps.com
License: UNKNOWN
Platform: UNKNOWN
Classifier: Development Status :: 5 - Production/Stable
Classifier: Environment :: Web Environment
Classifier: Framework :: Django
Classifier: Intended Audience :: Developers
Classifier: License :: OSI Approved :: BSD License
Classifier: Operating System :: OS Independent
Classifier: Programming Language :: Python
Classifier: Topic :: Software Development
Classifier: Topic :: Software Development :: Libraries :: Application Frameworks
